datastax/__init__.py
datastax/__main__.py
datastax/Arrays/PriorityQueue.py
datastax/Arrays/Queue.py
datastax/Arrays/Stack.py
datastax/Arrays/__init__.py
datastax/Arrays/AbstractArrays/Array.py
datastax/Arrays/AbstractArrays/Queue.py
datastax/Arrays/AbstractArrays/Stack.py
datastax/Arrays/AbstractArrays/__init__.py
datastax/Lists/CircularLinkedList.py
datastax/Lists/DoublyCircularList.py
datastax/Lists/DoublyLinkedList.py
datastax/Lists/LRUCache.py
datastax/Lists/LinkedList.py
datastax/Lists/Queue.py
datastax/Lists/__init__.py
datastax/Lists/AbstractLists/CircularLinkedList.py
datastax/Lists/AbstractLists/DoublyCircularList.py
datastax/Lists/AbstractLists/DoublyLinkedList.py
datastax/Lists/AbstractLists/LinkedList.py
datastax/Lists/AbstractLists/Queue.py
datastax/Lists/AbstractLists/__init__.py
datastax/Nodes/AVLNode.py
datastax/Nodes/DoublyNode.py
datastax/Nodes/HeapNode.py
datastax/Nodes/HuffmanNode.py
datastax/Nodes/Node.py
datastax/Nodes/RedBlackNode.py
datastax/Nodes/SegmentNode.py
datastax/Nodes/SplayNode.py
datastax/Nodes/ThreadedNode.py
datastax/Nodes/TreeNode.py
datastax/Nodes/__init__.py
datastax/Nodes/AbstractNodes/DoublyNode.py
datastax/Nodes/AbstractNodes/HuffmanNode.py
datastax/Nodes/AbstractNodes/Node.py
datastax/Nodes/AbstractNodes/RedBlackNode.py
datastax/Nodes/AbstractNodes/SegmentNode.py
datastax/Nodes/AbstractNodes/ThreadedNode.py
datastax/Nodes/AbstractNodes/TreeNode.py
datastax/Nodes/AbstractNodes/__init__.py
datastax/Tables/HuffmanTable.py
datastax/Tables/__init__.py
datastax/Tables/AbstractTables/HuffmanTable.py
datastax/Tables/AbstractTables/__init__.py
datastax/Trees/AVLTree.py
datastax/Trees/BinarySearchTree.py
datastax/Trees/BinaryTree.py
datastax/Trees/ExpressionTree.py
datastax/Trees/FibonacciTree.py
datastax/Trees/HeapTree.py
datastax/Trees/HuffmanTree.py
datastax/Trees/MinHeapTree.py
datastax/Trees/MinSegmentTree.py
datastax/Trees/RedBlackTree.py
datastax/Trees/SegmentTree.py
datastax/Trees/SplayTree.py
datastax-0.4.2.dist-info/LICENSE
datastax-0.4.2.dist-info/METADATA
datastax-0.4.2.dist-info/WHEEL
datastax-0.4.2.dist-info/top_level.txt
datastax-0.4.2.dist-info/RECORD
