Metadata-Version: 2.1
Name: datastax
Version: 0.4.2
Summary: A python library to handle dataStructures
Home-page: https://github.com/warmachine028/datastax
Download-URL: https://pypi.python.org/pypi/datastax
Author: Pritam K
Author-email: pritamkundu771@gmail.com
Maintainer: Pritam Kundu
License: MIT
Project-URL: Bug Tracker, https://github.com/warmachine028/datastax/issues
Project-URL: Documentation, https://github.com/warmachine028/datastax#readme
Project-URL: Source Code, https://github.com/warmachine028/datastax
Platform: Windows
Platform: Linux
Platform: Solaris
Platform: Mac OS-X
Platform: Unix
Classifier: Development Status :: 4 - Beta
Classifier: Intended Audience :: Education
Classifier: Intended Audience :: Developers
Classifier: Intended Audience :: End Users/Desktop
Classifier: Intended Audience :: Science/Research
Classifier: License :: OSI Approved :: MIT License
Classifier: Operating System :: OS Independent
Classifier: Programming Language :: Python :: 3.11
Classifier: Topic :: Documentation
Classifier: Topic :: Education :: Testing
Classifier: Topic :: Scientific/Engineering :: Visualization
Classifier: Topic :: Software Development :: Documentation
Classifier: Topic :: Software Development :: Libraries :: Python Modules
Classifier: Topic :: Software Development :: Testing :: Unit
Classifier: Typing :: Typed
Requires-Python: >3.11
License-File: LICENSE
